RangKaifaZidonghuaXilieZhuanlan/README.md
RangKaifaZidonghuaXilieZhuanlan/__init__.py
RangKaifaZidonghuaXilieZhuanlan/__main__.py
RangKaifaZidonghuaXilieZhuanlan/file.epub
RangKaifaZidonghuaXilieZhuanlan/index.html
RangKaifaZidonghuaXilieZhuanlan/css/__init__.py
RangKaifaZidonghuaXilieZhuanlan/css/annotations.css
RangKaifaZidonghuaXilieZhuanlan/css/main.css
RangKaifaZidonghuaXilieZhuanlan/css/normalize.css
RangKaifaZidonghuaXilieZhuanlan/css/popup.css
RangKaifaZidonghuaXilieZhuanlan/font/__init__.py
RangKaifaZidonghuaXilieZhuanlan/font/fontello.eot
RangKaifaZidonghuaXilieZhuanlan/font/fontello.svg
RangKaifaZidonghuaXilieZhuanlan/font/fontello.ttf
RangKaifaZidonghuaXilieZhuanlan/font/fontello.woff
RangKaifaZidonghuaXilieZhuanlan/img/__init__.py
RangKaifaZidonghuaXilieZhuanlan/img/annotator-glyph-sprite.png
RangKaifaZidonghuaXilieZhuanlan/img/annotator-icon-sprite.png
RangKaifaZidonghuaXilieZhuanlan/img/apple-touch-icon.png
RangKaifaZidonghuaXilieZhuanlan/img/cancelfullscreen.png
RangKaifaZidonghuaXilieZhuanlan/img/close.png
RangKaifaZidonghuaXilieZhuanlan/img/fullscreen.png
RangKaifaZidonghuaXilieZhuanlan/img/loader.gif
RangKaifaZidonghuaXilieZhuanlan/img/menu-icon.png
RangKaifaZidonghuaXilieZhuanlan/img/save.png
RangKaifaZidonghuaXilieZhuanlan/img/saved.png
RangKaifaZidonghuaXilieZhuanlan/img/settings-s.png
RangKaifaZidonghuaXilieZhuanlan/img/settings.png
RangKaifaZidonghuaXilieZhuanlan/img/star.png
RangKaifaZidonghuaXilieZhuanlan/js/__init__.py
RangKaifaZidonghuaXilieZhuanlan/js/epub.js
RangKaifaZidonghuaXilieZhuanlan/js/epub.min.js
RangKaifaZidonghuaXilieZhuanlan/js/epub.min.map
RangKaifaZidonghuaXilieZhuanlan/js/hooks.min.js
RangKaifaZidonghuaXilieZhuanlan/js/hooks.min.map
RangKaifaZidonghuaXilieZhuanlan/js/reader.js
RangKaifaZidonghuaXilieZhuanlan/js/reader.js.map
RangKaifaZidonghuaXilieZhuanlan/js/reader.min.js
RangKaifaZidonghuaXilieZhuanlan/js/reader.min.map
RangKaifaZidonghuaXilieZhuanlan/js/hooks/__init__.py
rang_kaifa_zidonghua_xilie_zhuanlan-2024.3.2.0.dist-info/METADATA
rang_kaifa_zidonghua_xilie_zhuanlan-2024.3.2.0.dist-info/WHEEL
rang_kaifa_zidonghua_xilie_zhuanlan-2024.3.2.0.dist-info/entry_points.txt
rang_kaifa_zidonghua_xilie_zhuanlan-2024.3.2.0.dist-info/top_level.txt
rang_kaifa_zidonghua_xilie_zhuanlan-2024.3.2.0.dist-info/RECORD
